README.rst
setup.py
taskwarrior_time_tracking_hook/__init__.py
taskwarrior_time_tracking_hook.egg-info/PKG-INFO
taskwarrior_time_tracking_hook.egg-info/SOURCES.txt
taskwarrior_time_tracking_hook.egg-info/dependency_links.txt
taskwarrior_time_tracking_hook.egg-info/entry_points.txt
taskwarrior_time_tracking_hook.egg-info/requires.txt
taskwarrior_time_tracking_hook.egg-info/top_level.txt