Metadata-Version: 1.1
Name: taskwarrior-time-tracking-hook
Version: 0.1.4
Summary: Track your time in a UDA in taskwarrior
Home-page: https://github.com/coddingtonbear/taskwarrior-time-tracking-hook
Author: Adam Coddington
Author-email: me@adamcoddington.net
License: UNKNOWN
Platform: UNKNOWN
Classifier: License :: OSI Approved :: MIT License
Classifier: Operating System :: OS Independent
